fortinet_wrapper/__init__.py
fortinet_wrapper/config.py
fortinet_wrapper/fortios.py
fortinet_wrapper/fortiswitch.py
fortinet_wrapper/testing.py
fortinet_wrapper-0.2.2.dist-info/licenses/LICENSE
fortinet_wrapper-0.2.2.dist-info/METADATA
fortinet_wrapper-0.2.2.dist-info/WHEEL
fortinet_wrapper-0.2.2.dist-info/top_level.txt
fortinet_wrapper-0.2.2.dist-info/RECORD
