Metadata-Version: 2.4
Name: fortinet_wrapper
Version: 0.2.2
Summary: Fortinet Wrapper is a Python wrapper for the FortiOS API.
Home-page: https://github.com/HBNetNetworks/fortinet-wrapper
Author: HBNet Networks
Author-email: HBNet Networks <dev@hbnet.tech>
License: GPL-3.0-or-later
Project-URL: Homepage, https://github.com/HNBetNetworks/fortinet-wrapper
Project-URL: Repository, https://github.com/HNBetNetworks/fortinet-wrapper
Project-URL: Issues, https://github.com/HNBetNetworks/fortinet-wrapper/issues
Requires-Python: >=3.10
License-File: LICENSE
Dynamic: author
Dynamic: home-page
Dynamic: license-file
Dynamic: requires-python
